mcp_proxy/__init__.py
mcp_proxy/auth.py
mcp_proxy/cache.py
mcp_proxy/config.py
mcp_proxy/custom_tools.py
mcp_proxy/exceptions.py
mcp_proxy/hooks.py
mcp_proxy/models.py
mcp_proxy/nginx.py
mcp_proxy/parallel.py
mcp_proxy/search.py
mcp_proxy/utils.py
mcp_proxy/views.py
mcp_proxy/cli/__init__.py
mcp_proxy/cli/commands.py
mcp_proxy/cli/nginx.py
mcp_proxy/cli/server.py
mcp_proxy/cli/utils.py
mcp_proxy/cli/view.py
mcp_proxy/proxy/__init__.py
mcp_proxy/proxy/client.py
mcp_proxy/proxy/proxy.py
mcp_proxy/proxy/schema.py
mcp_proxy/proxy/tool_info.py
mcp_proxy/proxy/tools.py
mcp_proxy/tools/__init__.py
mcp_proxy/tools/github.py
mcp_proxy/tools/mfcqi.py
easy_mcp_proxy-0.2.0.dist-info/METADATA
easy_mcp_proxy-0.2.0.dist-info/WHEEL
easy_mcp_proxy-0.2.0.dist-info/entry_points.txt
easy_mcp_proxy-0.2.0.dist-info/licenses/LICENSE
easy_mcp_proxy-0.2.0.dist-info/RECORD
