Metadata-Version: 2.4
Name: easy-mcp-proxy
Version: 0.2.0
Summary: Easy MCP Proxy - Filter, transform, and compose MCP tools
Author-email: Andrew Brookins <a@andrewbrookins.com>
License-Expression: AGPL-3.0-or-later
License-File: LICENSE
Requires-Python: >=3.11
Requires-Dist: click>=8.0.0
Requires-Dist: faiss-cpu>=1.7.0
Requires-Dist: fastmcp>=2.0.0
Requires-Dist: httpx>=0.28.1
Requires-Dist: numpy>=1.24.0
Requires-Dist: pydantic>=2.0.0
Requires-Dist: python-dotenv>=1.2.1
Requires-Dist: python-ulid>=3.1.0
Requires-Dist: pyyaml>=6.0
Requires-Dist: rapidfuzz>=3.14.3
Requires-Dist: sentence-transformers>=2.2.0
Requires-Dist: wsproto>=1.3.2
